{
  "lesson1": [
    {"hanzi":"你好","pinyin":"nǐ hǎo","en":"hello"},
    {"hanzi":"再见","pinyin":"zài jiàn","en":"goodbye"},
    {"hanzi":"谢谢","pinyin":"xiè xie","en":"thank you"},
    {"hanzi":"不客气","pinyin":"bú kè qi","en":"you're welcome"},
    {"hanzi":"请","pinyin":"qǐng","en":"please"},
    {"hanzi":"对不起","pinyin":"duì bu qǐ","en":"sorry"},
    {"hanzi":"没关系","pinyin":"méi guān xi","en":"it's ok"}
  ],

  "lesson2": [
    {"hanzi":"一","pinyin":"yī","en":"one"},
    {"hanzi":"二","pinyin":"èr","en":"two"},
    {"hanzi":"三","pinyin":"sān","en":"three"},
    {"hanzi":"四","pinyin":"sì","en":"four"},
    {"hanzi":"五","pinyin":"wǔ","en":"five"},
    {"hanzi":"六","pinyin":"liù","en":"six"},
    {"hanzi":"七","pinyin":"qī","en":"seven"},
    {"hanzi":"八","pinyin":"bā","en":"eight"},
    {"hanzi":"九","pinyin":"jiǔ","en":"nine"},
    {"hanzi":"十","pinyin":"shí","en":"ten"}
  ],

  "lesson3": [
    {"hanzi":"我","pinyin":"wǒ","en":"I"},
    {"hanzi":"你","pinyin":"nǐ","en":"you"},
    {"hanzi":"他","pinyin":"tā","en":"he"},
    {"hanzi":"她","pinyin":"tā","en":"she"},
    {"hanzi":"它","pinyin":"tā","en":"it"},
    {"hanzi":"我们","pinyin":"wǒ men","en":"we"},
    {"hanzi":"你们","pinyin":"nǐ men","en":"you (plural)"},
    {"hanzi":"他们","pinyin":"tā men","en":"they"}
  ],

  "lesson4": [
    {"hanzi":"是","pinyin":"shì","en":"to be"},
    {"hanzi":"不是","pinyin":"bú shì","en":"not be"},
    {"hanzi":"有","pinyin":"yǒu","en":"to have"},
    {"hanzi":"没有","pinyin":"méi yǒu","en":"not have"},
    {"hanzi":"在","pinyin":"zài","en":"at"},
    {"hanzi":"这","pinyin":"zhè","en":"this"},
    {"hanzi":"那","pinyin":"nà","en":"that"}
  ],

  "lesson5": [
    {"hanzi":"哪","pinyin":"nǎ","en":"which"},
    {"hanzi":"什么","pinyin":"shén me","en":"what"},
    {"hanzi":"谁","pinyin":"shéi","en":"who"},
    {"hanzi":"怎么","pinyin":"zěn me","en":"how"},
    {"hanzi":"为什么","pinyin":"wèi shén me","en":"why"},
    {"hanzi":"多少","pinyin":"duō shǎo","en":"how many"}
  ],

  "lesson6": [
    {"hanzi":"大","pinyin":"dà","en":"big"},
    {"hanzi":"小","pinyin":"xiǎo","en":"small"},
    {"hanzi":"多","pinyin":"duō","en":"many"},
    {"hanzi":"少","pinyin":"shǎo","en":"few"},
    {"hanzi":"好","pinyin":"hǎo","en":"good"},
    {"hanzi":"坏","pinyin":"huài","en":"bad"}
  ],

  "lesson7": [
    {"hanzi":"吃","pinyin":"chī","en":"eat"},
    {"hanzi":"喝","pinyin":"hē","en":"drink"},
    {"hanzi":"看","pinyin":"kàn","en":"see"},
    {"hanzi":"听","pinyin":"tīng","en":"listen"},
    {"hanzi":"说","pinyin":"shuō","en":"speak"},
    {"hanzi":"读","pinyin":"dú","en":"read"},
    {"hanzi":"写","pinyin":"xiě","en":"write"}
  ],

  "lesson8": [
    {"hanzi":"喜欢","pinyin":"xǐ huān","en":"like"},
    {"hanzi":"爱","pinyin":"ài","en":"love"},
    {"hanzi":"想","pinyin":"xiǎng","en":"want"},
    {"hanzi":"要","pinyin":"yào","en":"want/need"},
    {"hanzi":"会","pinyin":"huì","en":"can"},
    {"hanzi":"能","pinyin":"néng","en":"able"}
  ],

  "lesson9": [
    {"hanzi":"家","pinyin":"jiā","en":"home"},
    {"hanzi":"学校","pinyin":"xué xiào","en":"school"},
    {"hanzi":"中国","pinyin":"zhōng guó","en":"China"},
    {"hanzi":"人","pinyin":"rén","en":"person"},
    {"hanzi":"老师","pinyin":"lǎo shī","en":"teacher"},
    {"hanzi":"学生","pinyin":"xué shēng","en":"student"}
  ],

  "lesson10": [
    {"hanzi":"今天","pinyin":"jīn tiān","en":"today"},
    {"hanzi":"明天","pinyin":"míng tiān","en":"tomorrow"},
    {"hanzi":"昨天","pinyin":"zuó tiān","en":"yesterday"},
    {"hanzi":"现在","pinyin":"xiàn zài","en":"now"},
    {"hanzi":"时候","pinyin":"shí hou","en":"time"},
    {"hanzi":"年","pinyin":"nián","en":"year"},
    {"hanzi":"月","pinyin":"yuè","en":"month"},
    {"hanzi":"日","pinyin":"rì","en":"day"}
  ]
}
